{
  "type": "PROGRAM",
  "loc": 0,
  "importDeclarations": [
    {
      "type": "IMPORT_DECLARATION",
      "loc": 7,
      "path": {
        "type": "identifier",
        "value": "io",
        "start": 7,
        "end": 8
      }
    }
  ],
  "typeDefinitions": [
    {
      "type": "TYPE_DEFINITION",
      "loc": 12,
      "name": {
        "type": "identifier",
        "value": "Point",
        "start": 17,
        "end": 21
      },
      "rhs": {
        "type": "GOM_TYPE_STRUCT",
        "loc": 25,
        "fields": [
          {
            "type": "GOM_TYPE_STRUCT_FIELD",
            "loc": 38,
            "name": {
              "type": "identifier",
              "value": "x",
              "start": 38,
              "end": 38
            },
            "fieldType": {
              "type": "GOM_TYPE_ID_OR_ARRAY",
              "loc": 41,
              "id": {
                "type": "built_in_type",
                "value": "i8",
                "start": 41,
                "end": 42
              }
            }
          },
          {
            "type": "GOM_TYPE_STRUCT_FIELD",
            "loc": 49,
            "name": {
              "type": "identifier",
              "value": "y",
              "start": 49,
              "end": 49
            },
            "fieldType": {
              "type": "GOM_TYPE_ID_OR_ARRAY",
              "loc": 52,
              "id": {
                "type": "built_in_type",
                "value": "i8",
                "start": 52,
                "end": 53
              }
            }
          }
        ]
      }
    }
  ],
  "globalVariables": [
    {
      "type": "LET_STATEMENT",
      "loc": 59,
      "decls": [
        {
          "type": "ASSIGNMENT",
          "loc": 63,
          "lhs": {
            "type": "TERM",
            "loc": 63,
            "token": {
              "type": "identifier",
              "value": "GLOBAL",
              "start": 63,
              "end": 68
            },
            "gomType": {
              "kind": "PrimitiveOrAlias",
              "typeString": "resolve_type@@GLOBAL"
            },
            "resultantType": {
              "kind": "PrimitiveOrAlias",
              "typeString": "i8"
            }
          },
          "rhs": {
            "type": "TERM",
            "loc": 72,
            "token": {
              "type": "numliteral",
              "value": "1",
              "start": 72,
              "end": 72
            },
            "gomType": {
              "kind": "PrimitiveOrAlias",
              "typeString": "i8"
            },
            "resultantType": {
              "kind": "PrimitiveOrAlias",
              "typeString": "i8"
            }
          },
          "resultantType": {
            "kind": "PrimitiveOrAlias",
            "typeString": "void"
          }
        }
      ]
    }
  ],
  "functionDeclarations": [
    {
      "type": "FUNCTION_DEFINITION",
      "loc": 76,
      "name": {
        "type": "identifier",
        "value": "square",
        "start": 79,
        "end": 84
      },
      "args": [
        {
          "type": "ARGUMENT_ITEM",
          "loc": 86,
          "name": {
            "type": "TERM",
            "loc": 86,
            "token": {
              "type": "identifier",
              "value": "x",
              "start": 86,
              "end": 86
            },
            "gomType": {
              "kind": "PrimitiveOrAlias",
              "typeString": "resolve_type@@x"
            },
            "resultantType": {
              "kind": "PrimitiveOrAlias",
              "typeString": "resolve_type@@x"
            }
          },
          "expectedType": {
            "type": "built_in_type",
            "value": "i8",
            "start": 89,
            "end": 90
          },
          "gomType": {
            "kind": "PrimitiveOrAlias",
            "typeString": "i8"
          }
        }
      ],
      "returnType": {
        "type": "FUNCTION_RETURN_TYPE",
        "loc": 92,
        "returnType": {
          "type": "built_in_type",
          "value": "i8",
          "start": 94,
          "end": 95
        }
      },
      "body": [
        {
          "type": "RETURN_STATEMENT",
          "loc": 103,
          "expr": {
            "type": "QUOT",
            "loc": 110,
            "lhs": {
              "type": "TERM",
              "loc": 110,
              "token": {
                "type": "identifier",
                "value": "x",
                "start": 110,
                "end": 110
              },
              "gomType": {
                "kind": "PrimitiveOrAlias",
                "typeString": "resolve_type@@x"
              },
              "resultantType": {
                "kind": "PrimitiveOrAlias",
                "typeString": "i8"
              }
            },
            "op": {
              "type": "*",
              "value": "*",
              "start": 112,
              "end": 112
            },
            "rhs": {
              "type": "TERM",
              "loc": 114,
              "token": {
                "type": "identifier",
                "value": "x",
                "start": 114,
                "end": 114
              },
              "gomType": {
                "kind": "PrimitiveOrAlias",
                "typeString": "resolve_type@@x"
              },
              "resultantType": {
                "kind": "PrimitiveOrAlias",
                "typeString": "i8"
              }
            },
            "resultantType": {
              "kind": "PrimitiveOrAlias",
              "typeString": "i8"
            }
          }
        }
      ],
      "gomType": {
        "kind": "Function",
        "args": [
          {
            "kind": "PrimitiveOrAlias",
            "typeString": "i8"
          }
        ],
        "returnType": {
          "kind": "PrimitiveOrAlias",
          "typeString": "i8"
        }
      }
    },
    {
      "type": "FUNCTION_DEFINITION",
      "loc": 120,
      "name": {
        "type": "identifier",
        "value": "add",
        "start": 123,
        "end": 125
      },
      "args": [
        {
          "type": "ARGUMENT_ITEM",
          "loc": 127,
          "name": {
            "type": "TERM",
            "loc": 127,
            "token": {
              "type": "identifier",
              "value": "a",
              "start": 127,
              "end": 127
            },
            "gomType": {
              "kind": "PrimitiveOrAlias",
              "typeString": "resolve_type@@a"
            },
            "resultantType": {
              "kind": "PrimitiveOrAlias",
              "typeString": "resolve_type@@a"
            }
          },
          "expectedType": {
            "type": "built_in_type",
            "value": "i8",
            "start": 130,
            "end": 131
          },
          "gomType": {
            "kind": "PrimitiveOrAlias",
            "typeString": "i8"
          }
        },
        {
          "type": "ARGUMENT_ITEM",
          "loc": 134,
          "name": {
            "type": "TERM",
            "loc": 134,
            "token": {
              "type": "identifier",
              "value": "b",
              "start": 134,
              "end": 134
            },
            "gomType": {
              "kind": "PrimitiveOrAlias",
              "typeString": "resolve_type@@b"
            },
            "resultantType": {
              "kind": "PrimitiveOrAlias",
              "typeString": "resolve_type@@b"
            }
          },
          "expectedType": {
            "type": "built_in_type",
            "value": "i8",
            "start": 137,
            "end": 138
          },
          "gomType": {
            "kind": "PrimitiveOrAlias",
            "typeString": "i8"
          }
        }
      ],
      "returnType": {
        "type": "FUNCTION_RETURN_TYPE",
        "loc": 140,
        "returnType": {
          "type": "built_in_type",
          "value": "i8",
          "start": 142,
          "end": 143
        }
      },
      "body": [
        {
          "type": "RETURN_STATEMENT",
          "loc": 151,
          "expr": {
            "type": "SUM",
            "loc": 158,
            "lhs": {
              "type": "TERM",
              "loc": 158,
              "token": {
                "type": "identifier",
                "value": "a",
                "start": 158,
                "end": 158
              },
              "gomType": {
                "kind": "PrimitiveOrAlias",
                "typeString": "resolve_type@@a"
              },
              "resultantType": {
                "kind": "PrimitiveOrAlias",
                "typeString": "i8"
              }
            },
            "op": {
              "type": "+",
              "value": "+",
              "start": 160,
              "end": 160
            },
            "rhs": {
              "type": "TERM",
              "loc": 162,
              "token": {
                "type": "identifier",
                "value": "b",
                "start": 162,
                "end": 162
              },
              "gomType": {
                "kind": "PrimitiveOrAlias",
                "typeString": "resolve_type@@b"
              },
              "resultantType": {
                "kind": "PrimitiveOrAlias",
                "typeString": "i8"
              }
            },
            "resultantType": {
              "kind": "PrimitiveOrAlias",
              "typeString": "i8"
            }
          }
        }
      ],
      "gomType": {
        "kind": "Function",
        "args": [
          {
            "kind": "PrimitiveOrAlias",
            "typeString": "i8"
          },
          {
            "kind": "PrimitiveOrAlias",
            "typeString": "i8"
          }
        ],
        "returnType": {
          "kind": "PrimitiveOrAlias",
          "typeString": "i8"
        }
      }
    }
  ],
  "mainFunction": {
    "type": "MAIN_FUNCTION",
    "loc": 171,
    "body": [
      {
        "type": "LET_STATEMENT",
        "loc": 184,
        "decls": [
          {
            "type": "ASSIGNMENT",
            "loc": 188,
            "lhs": {
              "type": "TERM",
              "loc": 188,
              "token": {
                "type": "identifier",
                "value": "a",
                "start": 188,
                "end": 188
              },
              "gomType": {
                "kind": "PrimitiveOrAlias",
                "typeString": "resolve_type@@a"
              },
              "resultantType": {
                "kind": "PrimitiveOrAlias",
                "typeString": "i8"
              }
            },
            "rhs": {
              "type": "SUM",
              "loc": 192,
              "lhs": {
                "type": "TERM",
                "loc": 192,
                "token": {
                  "type": "numliteral",
                  "value": "1",
                  "start": 192,
                  "end": 192
                },
                "gomType": {
                  "kind": "PrimitiveOrAlias",
                  "typeString": "i8"
                },
                "resultantType": {
                  "kind": "PrimitiveOrAlias",
                  "typeString": "i8"
                }
              },
              "op": {
                "type": "+",
                "value": "+",
                "start": 194,
                "end": 194
              },
              "rhs": {
                "type": "TERM",
                "loc": 196,
                "token": {
                  "type": "numliteral",
                  "value": "2",
                  "start": 196,
                  "end": 196
                },
                "gomType": {
                  "kind": "PrimitiveOrAlias",
                  "typeString": "i8"
                },
                "resultantType": {
                  "kind": "PrimitiveOrAlias",
                  "typeString": "i8"
                }
              },
              "resultantType": {
                "kind": "PrimitiveOrAlias",
                "typeString": "i8"
              }
            },
            "resultantType": {
              "kind": "PrimitiveOrAlias",
              "typeString": "void"
            }
          },
          {
            "type": "ASSIGNMENT",
            "loc": 199,
            "lhs": {
              "type": "TERM",
              "loc": 199,
              "token": {
                "type": "identifier",
                "value": "b",
                "start": 199,
                "end": 199
              },
              "gomType": {
                "kind": "PrimitiveOrAlias",
                "typeString": "resolve_type@@b"
              },
              "resultantType": {
                "kind": "PrimitiveOrAlias",
                "typeString": "i8"
              }
            },
            "rhs": {
              "type": "TERM",
              "loc": 203,
              "token": {
                "type": "numliteral",
                "value": "2",
                "start": 203,
                "end": 203
              },
              "gomType": {
                "kind": "PrimitiveOrAlias",
                "typeString": "i8"
              },
              "resultantType": {
                "kind": "PrimitiveOrAlias",
                "typeString": "i8"
              }
            },
            "resultantType": {
              "kind": "PrimitiveOrAlias",
              "typeString": "void"
            }
          }
        ]
      },
      {
        "type": "EXPRESSION_STATEMENT",
        "loc": 211,
        "expr": {
          "type": "CALL",
          "loc": 211,
          "id": {
            "type": "TERM",
            "loc": 211,
            "token": {
              "type": "identifier",
              "value": "add",
              "start": 211,
              "end": 213
            },
            "gomType": {
              "kind": "PrimitiveOrAlias",
              "typeString": "resolve_type@@add"
            },
            "resultantType": {
              "kind": "PrimitiveOrAlias",
              "typeString": "resolve_type@@add"
            }
          },
          "args": [
            {
              "type": "TERM",
              "loc": 215,
              "token": {
                "type": "numliteral",
                "value": "1",
                "start": 215,
                "end": 215
              },
              "gomType": {
                "kind": "PrimitiveOrAlias",
                "typeString": "i8"
              },
              "resultantType": {
                "kind": "PrimitiveOrAlias",
                "typeString": "i8"
              }
            },
            {
              "type": "EXPR_BRACKETED",
              "loc": 218,
              "expr": {
                "type": "SUM",
                "loc": 219,
                "lhs": {
                  "type": "TERM",
                  "loc": 219,
                  "token": {
                    "type": "numliteral",
                    "value": "1",
                    "start": 219,
                    "end": 219
                  },
                  "gomType": {
                    "kind": "PrimitiveOrAlias",
                    "typeString": "i8"
                  },
                  "resultantType": {
                    "kind": "PrimitiveOrAlias",
                    "typeString": "i8"
                  }
                },
                "op": {
                  "type": "+",
                  "value": "+",
                  "start": 221,
                  "end": 221
                },
                "rhs": {
                  "type": "QUOT",
                  "loc": 223,
                  "lhs": {
                    "type": "TERM",
                    "loc": 223,
                    "token": {
                      "type": "identifier",
                      "value": "b",
                      "start": 223,
                      "end": 223
                    },
                    "gomType": {
                      "kind": "PrimitiveOrAlias",
                      "typeString": "resolve_type@@b"
                    },
                    "resultantType": {
                      "kind": "PrimitiveOrAlias",
                      "typeString": "i8"
                    }
                  },
                  "op": {
                    "type": "/",
                    "value": "/",
                    "start": 225,
                    "end": 225
                  },
                  "rhs": {
                    "type": "TERM",
                    "loc": 227,
                    "token": {
                      "type": "numliteral",
                      "value": "2",
                      "start": 227,
                      "end": 227
                    },
                    "gomType": {
                      "kind": "PrimitiveOrAlias",
                      "typeString": "i8"
                    },
                    "resultantType": {
                      "kind": "PrimitiveOrAlias",
                      "typeString": "i8"
                    }
                  },
                  "resultantType": {
                    "kind": "PrimitiveOrAlias",
                    "typeString": "i8"
                  }
                },
                "resultantType": {
                  "kind": "PrimitiveOrAlias",
                  "typeString": "i8"
                }
              }
            }
          ],
          "resultantType": {
            "kind": "PrimitiveOrAlias",
            "typeString": "i8"
          }
        }
      },
      {
        "type": "EXPRESSION_STATEMENT",
        "loc": 237,
        "expr": {
          "type": "ASSIGNMENT",
          "loc": 237,
          "lhs": {
            "type": "TERM",
            "loc": 237,
            "token": {
              "type": "identifier",
              "value": "a",
              "start": 237,
              "end": 237
            },
            "gomType": {
              "kind": "PrimitiveOrAlias",
              "typeString": "resolve_type@@a"
            },
            "resultantType": {
              "kind": "PrimitiveOrAlias",
              "typeString": "resolve_type@@a"
            }
          },
          "rhs": {
            "type": "TERM",
            "loc": 241,
            "token": {
              "type": "numliteral",
              "value": "2",
              "start": 241,
              "end": 241
            },
            "gomType": {
              "kind": "PrimitiveOrAlias",
              "typeString": "i8"
            },
            "resultantType": {
              "kind": "PrimitiveOrAlias",
              "typeString": "i8"
            }
          },
          "resultantType": {
            "kind": "PrimitiveOrAlias",
            "typeString": "void"
          }
        }
      },
      {
        "type": "LET_STATEMENT",
        "loc": 248,
        "decls": [
          {
            "type": "ASSIGNMENT",
            "loc": 252,
            "lhs": {
              "type": "TERM",
              "loc": 252,
              "token": {
                "type": "identifier",
                "value": "sq",
                "start": 252,
                "end": 253
              },
              "gomType": {
                "kind": "PrimitiveOrAlias",
                "typeString": "resolve_type@@sq"
              },
              "resultantType": {
                "kind": "PrimitiveOrAlias",
                "typeString": "i8"
              }
            },
            "rhs": {
              "type": "CALL",
              "loc": 257,
              "id": {
                "type": "TERM",
                "loc": 257,
                "token": {
                  "type": "identifier",
                  "value": "square",
                  "start": 257,
                  "end": 262
                },
                "gomType": {
                  "kind": "PrimitiveOrAlias",
                  "typeString": "resolve_type@@square"
                },
                "resultantType": {
                  "kind": "PrimitiveOrAlias",
                  "typeString": "resolve_type@@square"
                }
              },
              "args": [
                {
                  "type": "TERM",
                  "loc": 264,
                  "token": {
                    "type": "identifier",
                    "value": "a",
                    "start": 264,
                    "end": 264
                  },
                  "gomType": {
                    "kind": "PrimitiveOrAlias",
                    "typeString": "resolve_type@@a"
                  },
                  "resultantType": {
                    "kind": "PrimitiveOrAlias",
                    "typeString": "i8"
                  }
                }
              ],
              "resultantType": {
                "kind": "PrimitiveOrAlias",
                "typeString": "i8"
              }
            },
            "resultantType": {
              "kind": "PrimitiveOrAlias",
              "typeString": "void"
            }
          }
        ]
      },
      {
        "type": "LET_STATEMENT",
        "loc": 272,
        "decls": [
          {
            "type": "ASSIGNMENT",
            "loc": 276,
            "lhs": {
              "type": "TERM",
              "loc": 276,
              "token": {
                "type": "identifier",
                "value": "i",
                "start": 276,
                "end": 276
              },
              "gomType": {
                "kind": "PrimitiveOrAlias",
                "typeString": "resolve_type@@i"
              },
              "resultantType": {
                "kind": "PrimitiveOrAlias",
                "typeString": "i8"
              }
            },
            "rhs": {
              "type": "TERM",
              "loc": 280,
              "token": {
                "type": "numliteral",
                "value": "0",
                "start": 280,
                "end": 280
              },
              "gomType": {
                "kind": "PrimitiveOrAlias",
                "typeString": "i8"
              },
              "resultantType": {
                "kind": "PrimitiveOrAlias",
                "typeString": "i8"
              }
            },
            "resultantType": {
              "kind": "PrimitiveOrAlias",
              "typeString": "void"
            }
          }
        ]
      },
      {
        "type": "EXPRESSION_STATEMENT",
        "loc": 287,
        "expr": {
          "type": "CALL",
          "loc": 287,
          "id": {
            "type": "TERM",
            "loc": 287,
            "token": {
              "type": "identifier",
              "value": "add",
              "start": 287,
              "end": 289
            },
            "gomType": {
              "kind": "PrimitiveOrAlias",
              "typeString": "resolve_type@@add"
            },
            "resultantType": {
              "kind": "PrimitiveOrAlias",
              "typeString": "resolve_type@@add"
            }
          },
          "args": [
            {
              "type": "TERM",
              "loc": 291,
              "token": {
                "type": "identifier",
                "value": "i",
                "start": 291,
                "end": 291
              },
              "gomType": {
                "kind": "PrimitiveOrAlias",
                "typeString": "resolve_type@@i"
              },
              "resultantType": {
                "kind": "PrimitiveOrAlias",
                "typeString": "i8"
              }
            },
            {
              "type": "TERM",
              "loc": 294,
              "token": {
                "type": "numliteral",
                "value": "1",
                "start": 294,
                "end": 294
              },
              "gomType": {
                "kind": "PrimitiveOrAlias",
                "typeString": "i8"
              },
              "resultantType": {
                "kind": "PrimitiveOrAlias",
                "typeString": "i8"
              }
            }
          ],
          "resultantType": {
            "kind": "PrimitiveOrAlias",
            "typeString": "i8"
          }
        }
      }
    ]
  }
}